{
    "version": "0.4",
    "title": "Menu",
    "type": "section",
    "metadata": {
        "template_type": "section",
        "elementor_pro_required": false,
        "wp_page_template": "default"
    },
    "content": [
        {
            "id": "1d8655ba",
            "settings": {
                "gap": "no",
                "custom_height": {
                    "unit": "px",
                    "size": 900
                },
                "content_position": "middle",
                "padding": {
                    "unit": "px",
                    "top": "80",
                    "right": "0",
                    "bottom": "50",
                    "left": "0",
                    "isLinked": false
                },
                "padding_tablet": {
                    "unit": "px",
                    "top": "100",
                    "right": "25",
                    "bottom": "100",
                    "left": "25",
                    "isLinked": false
                },
                "padding_mobile": {
                    "unit": "px",
                    "top": "50",
                    "right": "20",
                    "bottom": "50",
                    "left": "20",
                    "isLinked": false
                },
                "height": "full",
                "background_background": "classic",
                "background_image": {
                    "url": "https:\/\/wp.envatoextensions.com\/collection-50\/wp-content\/uploads\/sites\/53\/2018\/07\/photo-1524350876685-274059332603.jpeg",
                    "id": 194
                },
                "background_overlay_background": "classic",
                "background_overlay_color": "#0c0c0c",
                "background_overlay_opacity": {
                    "unit": "px",
                    "size": 0.82999999999999996
                }
            },
            "elements": [
                {
                    "id": "2ff9c62a",
                    "settings": {
                        "_column_size": 100,
                        "space_between_widgets": 0
                    },
                    "elements": [
                        {
                            "id": "7f6fae5a",
                            "settings": {
                                "content_width": {
                                    "unit": "px",
                                    "size": 1000
                                },
                                "content_position": "top"
                            },
                            "elements": [
                                {
                                    "id": "381c6f68",
                                    "settings": {
                                        "_column_size": 100,
                                        "_inline_size": null
                                    },
                                    "elements": [
                                        {
                                            "id": "41b3241c",
                                            "settings": {
                                                "title": "Menu",
                                                "title_color": "#c4b583",
                                                "typography_typography": "custom",
                                                "typography_font_family": "Josefin Sans",
                                                "typography_font_size": {
                                                    "unit": "px",
                                                    "size": 17
                                                },
                                                "typography_font_weight": "600",
                                                "typography_text_transform": "uppercase",
                                                "typography_letter_spacing": {
                                                    "unit": "px",
                                                    "size": 4
                                                },
                                                "_margin": {
                                                    "unit": "px",
                                                    "top": "0",
                                                    "right": "0",
                                                    "bottom": "0",
                                                    "left": "0",
                                                    "isLinked": false
                                                },
                                                "align": "center"
                                            },
                                            "elements": [],
                                            "isInner": false,
                                            "widgetType": "heading",
                                            "elType": "widget"
                                        },
                                        {
                                            "id": "15dae23f",
                                            "settings": {
                                                "title": "Coffee & Espresso",
                                                "align": "center",
                                                "title_color": "#ffffff",
                                                "typography_typography": "custom",
                                                "typography_font_size": {
                                                    "unit": "px",
                                                    "size": 44
                                                },
                                                "typography_font_weight": "700",
                                                "typography_text_transform": "uppercase",
                                                "typography_line_height": {
                                                    "unit": "em",
                                                    "size": 1.25
                                                },
                                                "typography_letter_spacing": {
                                                    "unit": "px",
                                                    "size": 6
                                                },
                                                "_margin": {
                                                    "unit": "px",
                                                    "top": "0",
                                                    "right": "0",
                                                    "bottom": "0",
                                                    "left": "0",
                                                    "isLinked": false
                                                }
                                            },
                                            "elements": [],
                                            "isInner": false,
                                            "widgetType": "heading",
                                            "elType": "widget"
                                        }
                                    ],
                                    "isInner": true,
                                    "elType": "column"
                                }
                            ],
                            "isInner": true,
                            "elType": "section"
                        },
                        {
                            "id": "5295a1aa",
                            "settings": {
                                "weight": {
                                    "unit": "px",
                                    "size": 2
                                },
                                "color": "#c4b583",
                                "width": {
                                    "unit": "px",
                                    "size": 30
                                },
                                "align": "center"
                            },
                            "elements": [],
                            "isInner": false,
                            "widgetType": "divider",
                            "elType": "widget"
                        },
                        {
                            "id": "50180105",
                            "settings": {
                                "structure": "40",
                                "margin": {
                                    "unit": "px",
                                    "top": "30",
                                    "right": 0,
                                    "bottom": "30",
                                    "left": 0,
                                    "isLinked": true
                                }
                            },
                            "elements": [
                                {
                                    "id": "269506d3",
                                    "settings": {
                                        "_column_size": 25,
                                        "_inline_size": 40,
                                        "space_between_widgets": 0
                                    },
                                    "elements": [
                                        {
                                            "id": "8c5d6c9",
                                            "settings": {
                                                "title": "Freshly Brewed Coffee",
                                                "title_color": "#ffffff",
                                                "typography_typography": "custom",
                                                "typography_font_size": {
                                                    "unit": "px",
                                                    "size": 17
                                                },
                                                "typography_font_weight": "500",
                                                "header_size": "h6",
                                                "typography_text_transform": "uppercase",
                                                "_margin": {
                                                    "unit": "px",
                                                    "top": "0",
                                                    "right": "0",
                                                    "bottom": "-15",
                                                    "left": "0",
                                                    "isLinked": false
                                                }
                                            },
                                            "elements": [],
                                            "isInner": false,
                                            "widgetType": "heading",
                                            "elType": "widget"
                                        },
                                        {
                                            "id": "4d61294e",
                                            "settings": {
                                                "editor": "<p>Raclette subway tile etsy small batch<\/p>",
                                                "text_color": "rgba(255,255,255,0.79)",
                                                "typography_typography": "custom",
                                                "typography_font_weight": "200",
                                                "typography_font_size": {
                                                    "unit": "px",
                                                    "size": 16
                                                },
                                                "typography_line_height": {
                                                    "unit": "em",
                                                    "size": 1.6000000000000001
                                                }
                                            },
                                            "elements": [],
                                            "isInner": false,
                                            "widgetType": "text-editor",
                                            "elType": "widget"
                                        }
                                    ],
                                    "isInner": true,
                                    "elType": "column"
                                },
                                {
                                    "id": "37eb7cf5",
                                    "settings": {
                                        "_column_size": 25,
                                        "_inline_size": 10,
                                        "space_between_widgets": 0
                                    },
                                    "elements": [
                                        {
                                            "id": "1122b108",
                                            "settings": {
                                                "title": "$1.75",
                                                "title_color": "#ffffff",
                                                "typography_typography": "custom",
                                                "typography_font_size": {
                                                    "unit": "px",
                                                    "size": 35
                                                },
                                                "typography_font_weight": "300",
                                                "header_size": "h6",
                                                "typography_text_transform": "uppercase",
                                                "_margin": {
                                                    "unit": "px",
                                                    "top": "0",
                                                    "right": "0",
                                                    "bottom": "-15",
                                                    "left": "0",
                                                    "isLinked": false
                                                },
                                                "_border_width": {
                                                    "unit": "px",
                                                    "top": "0",
                                                    "right": "0",
                                                    "bottom": "2",
                                                    "left": "0",
                                                    "isLinked": false
                                                },
                                                "_border_color": "#c4b583"
                                            },
                                            "elements": [],
                                            "isInner": false,
                                            "widgetType": "heading",
                                            "elType": "widget"
                                        }
                                    ],
                                    "isInner": true,
                                    "elType": "column"
                                },
                                {
                                    "id": "550fc536",
                                    "settings": {
                                        "_column_size": 25,
                                        "_inline_size": 40,
                                        "space_between_widgets": 0
                                    },
                                    "elements": [
                                        {
                                            "id": "42249ad6",
                                            "settings": {
                                                "title": "Caramel Macchiato",
                                                "title_color": "#ffffff",
                                                "typography_typography": "custom",
                                                "typography_font_size": {
                                                    "unit": "px",
                                                    "size": 17
                                                },
                                                "typography_font_weight": "500",
                                                "header_size": "h6",
                                                "typography_text_transform": "uppercase",
                                                "_margin": {
                                                    "unit": "px",
                                                    "top": "0",
                                                    "right": "0",
                                                    "bottom": "-15",
                                                    "left": "0",
                                                    "isLinked": false
                                                }
                                            },
                                            "elements": [],
                                            "isInner": false,
                                            "widgetType": "heading",
                                            "elType": "widget"
                                        },
                                        {
                                            "id": "52803086",
                                            "settings": {
                                                "editor": "<p>Goth jianbing unicorn\u00a0<\/p>",
                                                "text_color": "rgba(255,255,255,0.79)",
                                                "typography_typography": "custom",
                                                "typography_font_weight": "200",
                                                "typography_line_height": {
                                                    "unit": "em",
                                                    "size": 1.6000000000000001
                                                }
                                            },
                                            "elements": [],
                                            "isInner": false,
                                            "widgetType": "text-editor",
                                            "elType": "widget"
                                        }
                                    ],
                                    "isInner": true,
                                    "elType": "column"
                                },
                                {
                                    "id": "3342c565",
                                    "settings": {
                                        "_column_size": 25,
                                        "_inline_size": 10,
                                        "space_between_widgets": 0
                                    },
                                    "elements": [
                                        {
                                            "id": "7120125c",
                                            "settings": {
                                                "title": "$3.25",
                                                "title_color": "#ffffff",
                                                "typography_typography": "custom",
                                                "typography_font_size": {
                                                    "unit": "px",
                                                    "size": 35
                                                },
                                                "typography_font_weight": "300",
                                                "header_size": "h6",
                                                "typography_text_transform": "uppercase",
                                                "_margin": {
                                                    "unit": "px",
                                                    "top": "0",
                                                    "right": "0",
                                                    "bottom": "-15",
                                                    "left": "0",
                                                    "isLinked": false
                                                }
                                            },
                                            "elements": [],
                                            "isInner": false,
                                            "widgetType": "heading",
                                            "elType": "widget"
                                        }
                                    ],
                                    "isInner": true,
                                    "elType": "column"
                                }
                            ],
                            "isInner": true,
                            "elType": "section"
                        },
                        {
                            "id": "3aa360d9",
                            "settings": {
                                "structure": "40",
                                "margin": {
                                    "unit": "px",
                                    "top": "30",
                                    "right": 0,
                                    "bottom": "30",
                                    "left": 0,
                                    "isLinked": true
                                }
                            },
                            "elements": [
                                {
                                    "id": "77ae46c6",
                                    "settings": {
                                        "_column_size": 25,
                                        "_inline_size": 40,
                                        "space_between_widgets": 0
                                    },
                                    "elements": [
                                        {
                                            "id": "29476631",
                                            "settings": {
                                                "title": "Iced Coffee",
                                                "title_color": "#ffffff",
                                                "typography_typography": "custom",
                                                "typography_font_size": {
                                                    "unit": "px",
                                                    "size": 17
                                                },
                                                "typography_font_weight": "500",
                                                "header_size": "h6",
                                                "typography_text_transform": "uppercase",
                                                "_margin": {
                                                    "unit": "px",
                                                    "top": "0",
                                                    "right": "0",
                                                    "bottom": "-15",
                                                    "left": "0",
                                                    "isLinked": false
                                                }
                                            },
                                            "elements": [],
                                            "isInner": false,
                                            "widgetType": "heading",
                                            "elType": "widget"
                                        },
                                        {
                                            "id": "1e076362",
                                            "settings": {
                                                "editor": "<p>Organic lo-fi helvetica iceland<\/p>",
                                                "text_color": "rgba(255,255,255,0.79)",
                                                "typography_typography": "custom",
                                                "typography_font_weight": "200",
                                                "typography_line_height": {
                                                    "unit": "em",
                                                    "size": 1.6000000000000001
                                                }
                                            },
                                            "elements": [],
                                            "isInner": false,
                                            "widgetType": "text-editor",
                                            "elType": "widget"
                                        }
                                    ],
                                    "isInner": true,
                                    "elType": "column"
                                },
                                {
                                    "id": "562d96fc",
                                    "settings": {
                                        "_column_size": 25,
                                        "_inline_size": 10,
                                        "space_between_widgets": 0
                                    },
                                    "elements": [
                                        {
                                            "id": "2a113596",
                                            "settings": {
                                                "title": "$2.25",
                                                "title_color": "#ffffff",
                                                "typography_typography": "custom",
                                                "typography_font_size": {
                                                    "unit": "px",
                                                    "size": 35
                                                },
                                                "typography_font_weight": "300",
                                                "header_size": "h6",
                                                "typography_text_transform": "uppercase",
                                                "_margin": {
                                                    "unit": "px",
                                                    "top": "0",
                                                    "right": "0",
                                                    "bottom": "-15",
                                                    "left": "0",
                                                    "isLinked": false
                                                }
                                            },
                                            "elements": [],
                                            "isInner": false,
                                            "widgetType": "heading",
                                            "elType": "widget"
                                        }
                                    ],
                                    "isInner": true,
                                    "elType": "column"
                                },
                                {
                                    "id": "37b04823",
                                    "settings": {
                                        "_column_size": 25,
                                        "_inline_size": 40,
                                        "space_between_widgets": 0
                                    },
                                    "elements": [
                                        {
                                            "id": "4908d582",
                                            "settings": {
                                                "title": "White Chocolate Mocha",
                                                "title_color": "#ffffff",
                                                "typography_typography": "custom",
                                                "typography_font_size": {
                                                    "unit": "px",
                                                    "size": 17
                                                },
                                                "typography_font_weight": "500",
                                                "header_size": "h6",
                                                "typography_text_transform": "uppercase",
                                                "_margin": {
                                                    "unit": "px",
                                                    "top": "0",
                                                    "right": "0",
                                                    "bottom": "-15",
                                                    "left": "0",
                                                    "isLinked": false
                                                }
                                            },
                                            "elements": [],
                                            "isInner": false,
                                            "widgetType": "heading",
                                            "elType": "widget"
                                        },
                                        {
                                            "id": "47ace229",
                                            "settings": {
                                                "editor": "<p>Meggings stumptown everyday carry<\/p>",
                                                "text_color": "rgba(255,255,255,0.79)",
                                                "typography_typography": "custom",
                                                "typography_font_weight": "200",
                                                "typography_line_height": {
                                                    "unit": "em",
                                                    "size": 1.6000000000000001
                                                }
                                            },
                                            "elements": [],
                                            "isInner": false,
                                            "widgetType": "text-editor",
                                            "elType": "widget"
                                        }
                                    ],
                                    "isInner": true,
                                    "elType": "column"
                                },
                                {
                                    "id": "3207e525",
                                    "settings": {
                                        "_column_size": 25,
                                        "_inline_size": 10,
                                        "space_between_widgets": 0
                                    },
                                    "elements": [
                                        {
                                            "id": "1e53b9cd",
                                            "settings": {
                                                "title": "$4.25",
                                                "title_color": "#ffffff",
                                                "typography_typography": "custom",
                                                "typography_font_size": {
                                                    "unit": "px",
                                                    "size": 35
                                                },
                                                "typography_font_weight": "300",
                                                "header_size": "h6",
                                                "typography_text_transform": "uppercase",
                                                "_margin": {
                                                    "unit": "px",
                                                    "top": "0",
                                                    "right": "0",
                                                    "bottom": "-15",
                                                    "left": "0",
                                                    "isLinked": false
                                                }
                                            },
                                            "elements": [],
                                            "isInner": false,
                                            "widgetType": "heading",
                                            "elType": "widget"
                                        }
                                    ],
                                    "isInner": true,
                                    "elType": "column"
                                }
                            ],
                            "isInner": true,
                            "elType": "section"
                        },
                        {
                            "id": "33d005c8",
                            "settings": {
                                "structure": "40",
                                "margin": {
                                    "unit": "px",
                                    "top": "30",
                                    "right": 0,
                                    "bottom": "30",
                                    "left": 0,
                                    "isLinked": true
                                }
                            },
                            "elements": [
                                {
                                    "id": "20084f65",
                                    "settings": {
                                        "_column_size": 25,
                                        "_inline_size": 40,
                                        "space_between_widgets": 0
                                    },
                                    "elements": [
                                        {
                                            "id": "772cdb9d",
                                            "settings": {
                                                "title": "Caffe Americano",
                                                "title_color": "#ffffff",
                                                "typography_typography": "custom",
                                                "typography_font_size": {
                                                    "unit": "px",
                                                    "size": 17
                                                },
                                                "typography_font_weight": "500",
                                                "header_size": "h6",
                                                "typography_text_transform": "uppercase",
                                                "_margin": {
                                                    "unit": "px",
                                                    "top": "0",
                                                    "right": "0",
                                                    "bottom": "-15",
                                                    "left": "0",
                                                    "isLinked": false
                                                }
                                            },
                                            "elements": [],
                                            "isInner": false,
                                            "widgetType": "heading",
                                            "elType": "widget"
                                        },
                                        {
                                            "id": "488466da",
                                            "settings": {
                                                "editor": "<p>Hammock letterpress coloring book brooklyn<\/p>",
                                                "text_color": "rgba(255,255,255,0.79)",
                                                "typography_typography": "custom",
                                                "typography_font_weight": "200",
                                                "typography_line_height": {
                                                    "unit": "em",
                                                    "size": 1.6000000000000001
                                                }
                                            },
                                            "elements": [],
                                            "isInner": false,
                                            "widgetType": "text-editor",
                                            "elType": "widget"
                                        }
                                    ],
                                    "isInner": true,
                                    "elType": "column"
                                },
                                {
                                    "id": "f3f16b6",
                                    "settings": {
                                        "_column_size": 25,
                                        "_inline_size": 10,
                                        "space_between_widgets": 0
                                    },
                                    "elements": [
                                        {
                                            "id": "3e2451f9",
                                            "settings": {
                                                "title": "$3.75",
                                                "title_color": "#ffffff",
                                                "typography_typography": "custom",
                                                "typography_font_size": {
                                                    "unit": "px",
                                                    "size": 35
                                                },
                                                "typography_font_weight": "300",
                                                "header_size": "h6",
                                                "typography_text_transform": "uppercase",
                                                "_margin": {
                                                    "unit": "px",
                                                    "top": "0",
                                                    "right": "0",
                                                    "bottom": "-15",
                                                    "left": "0",
                                                    "isLinked": false
                                                }
                                            },
                                            "elements": [],
                                            "isInner": false,
                                            "widgetType": "heading",
                                            "elType": "widget"
                                        }
                                    ],
                                    "isInner": true,
                                    "elType": "column"
                                },
                                {
                                    "id": "7b83364c",
                                    "settings": {
                                        "_column_size": 25,
                                        "_inline_size": 40,
                                        "space_between_widgets": 0
                                    },
                                    "elements": [
                                        {
                                            "id": "6b650b02",
                                            "settings": {
                                                "title": "Caffe Mocha",
                                                "title_color": "#ffffff",
                                                "typography_typography": "custom",
                                                "typography_font_size": {
                                                    "unit": "px",
                                                    "size": 17
                                                },
                                                "typography_font_weight": "500",
                                                "header_size": "h6",
                                                "typography_text_transform": "uppercase",
                                                "_margin": {
                                                    "unit": "px",
                                                    "top": "0",
                                                    "right": "0",
                                                    "bottom": "-15",
                                                    "left": "0",
                                                    "isLinked": false
                                                }
                                            },
                                            "elements": [],
                                            "isInner": false,
                                            "widgetType": "heading",
                                            "elType": "widget"
                                        },
                                        {
                                            "id": "6e3de6f2",
                                            "settings": {
                                                "editor": "<p>Ramps wayfarers pitchfork<\/p>",
                                                "text_color": "rgba(255,255,255,0.79)",
                                                "typography_typography": "custom",
                                                "typography_font_weight": "200",
                                                "typography_line_height": {
                                                    "unit": "em",
                                                    "size": 1.6000000000000001
                                                }
                                            },
                                            "elements": [],
                                            "isInner": false,
                                            "widgetType": "text-editor",
                                            "elType": "widget"
                                        }
                                    ],
                                    "isInner": true,
                                    "elType": "column"
                                },
                                {
                                    "id": "76451c70",
                                    "settings": {
                                        "_column_size": 25,
                                        "_inline_size": 10,
                                        "space_between_widgets": 0
                                    },
                                    "elements": [
                                        {
                                            "id": "75da3a92",
                                            "settings": {
                                                "title": "$3.35",
                                                "title_color": "#ffffff",
                                                "typography_typography": "custom",
                                                "typography_font_size": {
                                                    "unit": "px",
                                                    "size": 35
                                                },
                                                "typography_font_weight": "300",
                                                "header_size": "h6",
                                                "typography_text_transform": "uppercase",
                                                "_margin": {
                                                    "unit": "px",
                                                    "top": "0",
                                                    "right": "0",
                                                    "bottom": "-15",
                                                    "left": "0",
                                                    "isLinked": false
                                                }
                                            },
                                            "elements": [],
                                            "isInner": false,
                                            "widgetType": "heading",
                                            "elType": "widget"
                                        }
                                    ],
                                    "isInner": true,
                                    "elType": "column"
                                }
                            ],
                            "isInner": true,
                            "elType": "section"
                        },
                        {
                            "id": "1b9d5a4b",
                            "settings": {
                                "structure": "40",
                                "margin": {
                                    "unit": "px",
                                    "top": "30",
                                    "right": 0,
                                    "bottom": "30",
                                    "left": 0,
                                    "isLinked": true
                                }
                            },
                            "elements": [
                                {
                                    "id": "67e4ce6c",
                                    "settings": {
                                        "_column_size": 25,
                                        "_inline_size": 40,
                                        "space_between_widgets": 0
                                    },
                                    "elements": [
                                        {
                                            "id": "2b1db8d8",
                                            "settings": {
                                                "title": "Flat White",
                                                "title_color": "#ffffff",
                                                "typography_typography": "custom",
                                                "typography_font_size": {
                                                    "unit": "px",
                                                    "size": 17
                                                },
                                                "typography_font_weight": "500",
                                                "header_size": "h6",
                                                "typography_text_transform": "uppercase",
                                                "_margin": {
                                                    "unit": "px",
                                                    "top": "0",
                                                    "right": "0",
                                                    "bottom": "-15",
                                                    "left": "0",
                                                    "isLinked": false
                                                }
                                            },
                                            "elements": [],
                                            "isInner": false,
                                            "widgetType": "heading",
                                            "elType": "widget"
                                        },
                                        {
                                            "id": "5c2a6814",
                                            "settings": {
                                                "editor": "<p>Chartreuse ramps selvage<\/p>",
                                                "text_color": "rgba(255,255,255,0.79)",
                                                "typography_typography": "custom",
                                                "typography_font_weight": "200",
                                                "typography_line_height": {
                                                    "unit": "em",
                                                    "size": 1.6000000000000001
                                                }
                                            },
                                            "elements": [],
                                            "isInner": false,
                                            "widgetType": "text-editor",
                                            "elType": "widget"
                                        }
                                    ],
                                    "isInner": true,
                                    "elType": "column"
                                },
                                {
                                    "id": "24eef9d2",
                                    "settings": {
                                        "_column_size": 25,
                                        "_inline_size": 10,
                                        "space_between_widgets": 0
                                    },
                                    "elements": [
                                        {
                                            "id": "5deace7e",
                                            "settings": {
                                                "title": "$2.85",
                                                "title_color": "#ffffff",
                                                "typography_typography": "custom",
                                                "typography_font_size": {
                                                    "unit": "px",
                                                    "size": 35
                                                },
                                                "typography_font_weight": "300",
                                                "header_size": "h6",
                                                "typography_text_transform": "uppercase",
                                                "_margin": {
                                                    "unit": "px",
                                                    "top": "0",
                                                    "right": "0",
                                                    "bottom": "-15",
                                                    "left": "0",
                                                    "isLinked": false
                                                }
                                            },
                                            "elements": [],
                                            "isInner": false,
                                            "widgetType": "heading",
                                            "elType": "widget"
                                        }
                                    ],
                                    "isInner": true,
                                    "elType": "column"
                                },
                                {
                                    "id": "7d0c081a",
                                    "settings": {
                                        "_column_size": 25,
                                        "_inline_size": 40,
                                        "space_between_widgets": 0
                                    },
                                    "elements": [
                                        {
                                            "id": "319ba51e",
                                            "settings": {
                                                "title": "S'mores",
                                                "title_color": "#ffffff",
                                                "typography_typography": "custom",
                                                "typography_font_size": {
                                                    "unit": "px",
                                                    "size": 17
                                                },
                                                "typography_font_weight": "500",
                                                "header_size": "h6",
                                                "typography_text_transform": "uppercase",
                                                "_margin": {
                                                    "unit": "px",
                                                    "top": "0",
                                                    "right": "0",
                                                    "bottom": "-15",
                                                    "left": "0",
                                                    "isLinked": false
                                                }
                                            },
                                            "elements": [],
                                            "isInner": false,
                                            "widgetType": "heading",
                                            "elType": "widget"
                                        },
                                        {
                                            "id": "4b749f91",
                                            "settings": {
                                                "editor": "<p>Vape keffiyeh DIY knausgaard<\/p>",
                                                "text_color": "rgba(255,255,255,0.79)",
                                                "typography_typography": "custom",
                                                "typography_font_weight": "200",
                                                "typography_line_height": {
                                                    "unit": "em",
                                                    "size": 1.6000000000000001
                                                }
                                            },
                                            "elements": [],
                                            "isInner": false,
                                            "widgetType": "text-editor",
                                            "elType": "widget"
                                        }
                                    ],
                                    "isInner": true,
                                    "elType": "column"
                                },
                                {
                                    "id": "477e0276",
                                    "settings": {
                                        "_column_size": 25,
                                        "_inline_size": 10,
                                        "space_between_widgets": 0
                                    },
                                    "elements": [
                                        {
                                            "id": "13f851c6",
                                            "settings": {
                                                "title": "$2.95",
                                                "title_color": "#ffffff",
                                                "typography_typography": "custom",
                                                "typography_font_size": {
                                                    "unit": "px",
                                                    "size": 35
                                                },
                                                "typography_font_weight": "300",
                                                "header_size": "h6",
                                                "typography_text_transform": "uppercase",
                                                "_margin": {
                                                    "unit": "px",
                                                    "top": "0",
                                                    "right": "0",
                                                    "bottom": "-15",
                                                    "left": "0",
                                                    "isLinked": false
                                                }
                                            },
                                            "elements": [],
                                            "isInner": false,
                                            "widgetType": "heading",
                                            "elType": "widget"
                                        }
                                    ],
                                    "isInner": true,
                                    "elType": "column"
                                }
                            ],
                            "isInner": true,
                            "elType": "section"
                        },
                        {
                            "id": "35c91a1a",
                            "settings": {
                                "structure": "40",
                                "margin": {
                                    "unit": "px",
                                    "top": "30",
                                    "right": 0,
                                    "bottom": "30",
                                    "left": 0,
                                    "isLinked": true
                                }
                            },
                            "elements": [
                                {
                                    "id": "8e59377",
                                    "settings": {
                                        "_column_size": 25,
                                        "_inline_size": 40,
                                        "space_between_widgets": 0
                                    },
                                    "elements": [
                                        {
                                            "id": "62a1a1ec",
                                            "settings": {
                                                "title": "Caffe Latte",
                                                "title_color": "#ffffff",
                                                "typography_typography": "custom",
                                                "typography_font_size": {
                                                    "unit": "px",
                                                    "size": 17
                                                },
                                                "typography_font_weight": "500",
                                                "header_size": "h6",
                                                "typography_text_transform": "uppercase",
                                                "_margin": {
                                                    "unit": "px",
                                                    "top": "0",
                                                    "right": "0",
                                                    "bottom": "-15",
                                                    "left": "0",
                                                    "isLinked": false
                                                }
                                            },
                                            "elements": [],
                                            "isInner": false,
                                            "widgetType": "heading",
                                            "elType": "widget"
                                        },
                                        {
                                            "id": "1721efad",
                                            "settings": {
                                                "editor": "<p>Humblebrag hell of health<\/p>",
                                                "text_color": "rgba(255,255,255,0.79)",
                                                "typography_typography": "custom",
                                                "typography_font_weight": "200",
                                                "typography_line_height": {
                                                    "unit": "em",
                                                    "size": 1.6000000000000001
                                                }
                                            },
                                            "elements": [],
                                            "isInner": false,
                                            "widgetType": "text-editor",
                                            "elType": "widget"
                                        }
                                    ],
                                    "isInner": true,
                                    "elType": "column"
                                },
                                {
                                    "id": "76435e0d",
                                    "settings": {
                                        "_column_size": 25,
                                        "_inline_size": 10,
                                        "space_between_widgets": 0
                                    },
                                    "elements": [
                                        {
                                            "id": "1ea0beb2",
                                            "settings": {
                                                "title": "$3.65",
                                                "title_color": "#ffffff",
                                                "typography_typography": "custom",
                                                "typography_font_size": {
                                                    "unit": "px",
                                                    "size": 35
                                                },
                                                "typography_font_weight": "300",
                                                "header_size": "h6",
                                                "typography_text_transform": "uppercase",
                                                "_margin": {
                                                    "unit": "px",
                                                    "top": "0",
                                                    "right": "0",
                                                    "bottom": "-15",
                                                    "left": "0",
                                                    "isLinked": false
                                                }
                                            },
                                            "elements": [],
                                            "isInner": false,
                                            "widgetType": "heading",
                                            "elType": "widget"
                                        }
                                    ],
                                    "isInner": true,
                                    "elType": "column"
                                },
                                {
                                    "id": "3a1341",
                                    "settings": {
                                        "_column_size": 25,
                                        "_inline_size": 40,
                                        "space_between_widgets": 0
                                    },
                                    "elements": [
                                        {
                                            "id": "5d2a69a0",
                                            "settings": {
                                                "title": "Vanilla Bean Creme",
                                                "title_color": "#ffffff",
                                                "typography_typography": "custom",
                                                "typography_font_size": {
                                                    "unit": "px",
                                                    "size": 17
                                                },
                                                "typography_font_weight": "500",
                                                "header_size": "h6",
                                                "typography_text_transform": "uppercase",
                                                "_margin": {
                                                    "unit": "px",
                                                    "top": "0",
                                                    "right": "0",
                                                    "bottom": "-15",
                                                    "left": "0",
                                                    "isLinked": false
                                                }
                                            },
                                            "elements": [],
                                            "isInner": false,
                                            "widgetType": "heading",
                                            "elType": "widget"
                                        },
                                        {
                                            "id": "274dbcc8",
                                            "settings": {
                                                "editor": "<p>Hella whatever before<\/p>",
                                                "text_color": "rgba(255,255,255,0.79)",
                                                "typography_typography": "custom",
                                                "typography_font_weight": "200",
                                                "typography_line_height": {
                                                    "unit": "em",
                                                    "size": 1.6000000000000001
                                                }
                                            },
                                            "elements": [],
                                            "isInner": false,
                                            "widgetType": "text-editor",
                                            "elType": "widget"
                                        }
                                    ],
                                    "isInner": true,
                                    "elType": "column"
                                },
                                {
                                    "id": "1d5553b1",
                                    "settings": {
                                        "_column_size": 25,
                                        "_inline_size": 10,
                                        "space_between_widgets": 0
                                    },
                                    "elements": [
                                        {
                                            "id": "5d95d9b7",
                                            "settings": {
                                                "title": "$1.55",
                                                "title_color": "#ffffff",
                                                "typography_typography": "custom",
                                                "typography_font_size": {
                                                    "unit": "px",
                                                    "size": 35
                                                },
                                                "typography_font_weight": "300",
                                                "header_size": "h6",
                                                "typography_text_transform": "uppercase",
                                                "_margin": {
                                                    "unit": "px",
                                                    "top": "0",
                                                    "right": "0",
                                                    "bottom": "-15",
                                                    "left": "0",
                                                    "isLinked": false
                                                }
                                            },
                                            "elements": [],
                                            "isInner": false,
                                            "widgetType": "heading",
                                            "elType": "widget"
                                        }
                                    ],
                                    "isInner": true,
                                    "elType": "column"
                                }
                            ],
                            "isInner": true,
                            "elType": "section"
                        }
                    ],
                    "isInner": false,
                    "elType": "column"
                }
            ],
            "isInner": false,
            "elType": "section"
        },
        {
            "id": "1e06cc93",
            "settings": {
                "stretch_section": "section-stretched",
                "custom_height": {
                    "unit": "px",
                    "size": 380
                },
                "content_position": "middle",
                "background_position": "top center",
                "background_repeat": "no-repeat",
                "background_size": "cover",
                "background_overlay_background": "classic",
                "background_overlay_color": "#131313",
                "padding": {
                    "unit": "px",
                    "top": "33",
                    "right": "0",
                    "bottom": "0",
                    "left": "0",
                    "isLinked": false
                },
                "height": "min-height",
                "background_overlay_opacity": {
                    "unit": "px",
                    "size": 0.65000000000000002
                }
            },
            "elements": [
                {
                    "id": "3395b46d",
                    "settings": {
                        "_column_size": 100,
                        "_inline_size": null,
                        "space_between_widgets": 30
                    },
                    "elements": [
                        {
                            "id": "5a0e52ae",
                            "settings": {
                                "title": "Book a table",
                                "title_color": "#c4b583",
                                "typography_typography": "custom",
                                "typography_font_family": "Josefin Sans",
                                "typography_font_size": {
                                    "unit": "px",
                                    "size": 17
                                },
                                "typography_font_weight": "600",
                                "typography_text_transform": "uppercase",
                                "typography_letter_spacing": {
                                    "unit": "px",
                                    "size": 4
                                },
                                "_margin": {
                                    "unit": "px",
                                    "top": "0",
                                    "right": "0",
                                    "bottom": "0",
                                    "left": "0",
                                    "isLinked": false
                                },
                                "align": "center"
                            },
                            "elements": [],
                            "isInner": false,
                            "widgetType": "heading",
                            "elType": "widget"
                        },
                        {
                            "id": "34a6c61f",
                            "settings": {
                                "title": "MAKE A RESERVATION",
                                "align": "center",
                                "title_color": "#0c0c0c",
                                "typography_typography": "custom",
                                "typography_font_family": "Josefin Sans",
                                "typography_font_size": {
                                    "unit": "px",
                                    "size": 44
                                },
                                "typography_font_weight": "700",
                                "typography_text_transform": "uppercase",
                                "typography_line_height": {
                                    "unit": "em",
                                    "size": 1.25
                                },
                                "typography_letter_spacing": {
                                    "unit": "px",
                                    "size": 6
                                },
                                "_margin": {
                                    "unit": "px",
                                    "top": "0",
                                    "right": "0",
                                    "bottom": "0",
                                    "left": "0",
                                    "isLinked": false
                                }
                            },
                            "elements": [],
                            "isInner": false,
                            "widgetType": "heading",
                            "elType": "widget"
                        },
                        {
                            "id": "3aa5645c",
                            "settings": {
                                "weight": {
                                    "unit": "px",
                                    "size": 2
                                },
                                "color": "#c4b583",
                                "width": {
                                    "unit": "px",
                                    "size": 30
                                },
                                "align": "center",
                                "gap": {
                                    "unit": "px",
                                    "size": 2
                                },
                                "_margin": {
                                    "unit": "px",
                                    "top": "-15",
                                    "right": "0",
                                    "bottom": "0",
                                    "left": "0",
                                    "isLinked": false
                                }
                            },
                            "elements": [],
                            "isInner": false,
                            "widgetType": "divider",
                            "elType": "widget"
                        },
                        {
                            "id": "139b1b2e",
                            "settings": {
                                "text": "Book now",
                                "align": "center",
                                "typography_typography": "custom",
                                "typography_font_size": {
                                    "unit": "px",
                                    "size": 13
                                },
                                "typography_font_weight": "600",
                                "typography_text_transform": "uppercase",
                                "button_text_color": "#ffffff",
                                "background_color": "#c4b583",
                                "hover_color": "#0c0c0c",
                                "button_background_hover_color": "#ffffff",
                                "hover_animation": "bounce-in",
                                "border_radius": {
                                    "unit": "px",
                                    "top": "100",
                                    "right": "100",
                                    "bottom": "100",
                                    "left": "100",
                                    "isLinked": true
                                },
                                "text_padding": {
                                    "unit": "px",
                                    "top": "15",
                                    "right": "45",
                                    "bottom": "15",
                                    "left": "45",
                                    "isLinked": false
                                },
                                "_padding": {
                                    "unit": "px",
                                    "top": "0",
                                    "right": "0",
                                    "bottom": "0",
                                    "left": "0",
                                    "isLinked": false
                                },
                                "typography_font_family": "Josefin Sans",
                                "typography_line_height": {
                                    "unit": "px",
                                    "size": 19
                                },
                                "typography_letter_spacing": {
                                    "unit": "px",
                                    "size": 1.8
                                },
                                "border_border": "solid",
                                "border_width": {
                                    "unit": "px",
                                    "top": "1",
                                    "right": "1",
                                    "bottom": "1",
                                    "left": "1",
                                    "isLinked": true
                                },
                                "border_color": "#ffffff"
                            },
                            "elements": [],
                            "isInner": false,
                            "widgetType": "button",
                            "elType": "widget"
                        }
                    ],
                    "isInner": false,
                    "elType": "column"
                }
            ],
            "isInner": false,
            "elType": "section"
        }
    ]
}